<?xml version='1.0' encoding='UTF-8'?>
<dataset>
  <TAXONBASE DTYPE="Taxon" ID="1000" CREATED="2012-06-07 20:44:50.0" UUID="f9802a03-626d-4c2b-a545-0c345160de70" PROTECTEDTITLECACHE="false" TITLECACHE="Abies sec. " DOUBTFUL="false" USENAMECACHE="false" EXCLUDED="false" TAXONSTATUSUNKNOWN="false" TAXONOMICCHILDRENCOUNT="0" UNPLACED="false" NAME_ID="1000" SEC_ID="1000"/>
  <TAXONBASE DTYPE="Taxon" ID="1001" CREATED="2012-06-07 20:44:50.0" UUID="d2bb0550-45cd-4167-a8e1-495778656344" PROTECTEDTITLECACHE="false" TITLECACHE="Abies alba sec. " DOUBTFUL="false" USENAMECACHE="false" EXCLUDED="false" TAXONSTATUSUNKNOWN="false" TAXONOMICCHILDRENCOUNT="0" UNPLACED="false" NAME_ID="1001" SEC_ID="1000"/>
  <TAXONBASE DTYPE="Taxon" ID="1002" CREATED="2012-06-07 20:44:50.0" UUID="d479ed68-93a6-4231-8664-cfec594ee1fe" PROTECTEDTITLECACHE="false" TITLECACHE="Abies balsamea sec. " DOUBTFUL="false" USENAMECACHE="false" EXCLUDED="false" TAXONSTATUSUNKNOWN="false" TAXONOMICCHILDRENCOUNT="0" UNPLACED="false" NAME_ID="1002" SEC_ID="1000"/>
  <TAXONBASE DTYPE="Taxon" ID="1003" CREATED="2012-06-07 20:44:50.0" UUID="2bccd67f-94f2-47ed-98de-760c6ec6de09" PROTECTEDTITLECACHE="false" TITLECACHE="Abies grandis sec. " DOUBTFUL="false" USENAMECACHE="false" EXCLUDED="false" TAXONSTATUSUNKNOWN="false" TAXONOMICCHILDRENCOUNT="0" UNPLACED="false" NAME_ID="1003" SEC_ID="1000"/>
  <TAXONBASE DTYPE="Taxon" ID="1004" CREATED="2012-06-07 20:44:50.0" UUID="993fe4a2-56dd-4cd7-a8b7-59cc21c77a86" PROTECTEDTITLECACHE="false" TITLECACHE="Abies kawakamii sec. " DOUBTFUL="false" USENAMECACHE="false" EXCLUDED="false" TAXONSTATUSUNKNOWN="false" TAXONOMICCHILDRENCOUNT="0" UNPLACED="false" NAME_ID="1004" SEC_ID="1000"/>
  <TAXONBASE DTYPE="Synonym" ID="1005" CREATED="2012-06-07 20:44:50.0" UUID="b882bb39-e9e2-4b00-bd95-470c540dff4f" PROTECTEDTITLECACHE="false" TITLECACHE="Abies subalpina sec. " DOUBTFUL="false" USENAMECACHE="false" NAME_ID="1005" SEC_ID="1000"/>
  <TAXONBASE DTYPE="Taxon" ID="1006" CREATED="2012-06-07 20:44:50.0" UUID="ac1a1336-4478-4820-89bb-c4f98d28b2f5" PROTECTEDTITLECACHE="false" TITLECACHE="Abies lasiocarpa sec. " DOUBTFUL="false" USENAMECACHE="false" EXCLUDED="false" TAXONSTATUSUNKNOWN="false" TAXONOMICCHILDRENCOUNT="0" UNPLACED="false" NAME_ID="1006" SEC_ID="1000"/>
  <TAXONNAMEBASE DTYPE="BotanicalName" ID="1000" CREATED="2012-06-07 20:44:50.0" UUID="c97b33f7-f19e-4360-9691-a21ee9ced088" PROTECTEDTITLECACHE="false" TITLECACHE="Abies" FULLTITLECACHE="Abies" PARSINGPROBLEM="0" PROBLEMENDS="-1" PROBLEMSTARTS="-1" PROTECTEDFULLTITLECACHE="false" AUTHORSHIPCACHE="" BINOMHYBRID="false" HYBRIDFORMULA="false" MONOMHYBRID="false" NAMECACHE="Abies" PROTECTEDAUTHORSHIPCACHE="false" PROTECTEDNAMECACHE="true" TRINOMHYBRID="false" ANAMORPHIC="false" HOMOTYPICALGROUP_ID="1000" RANK_ID="787"/>
  <TAXONNAMEBASE DTYPE="BotanicalName" ID="1001" CREATED="2012-06-07 20:44:50.0" UUID="1679cb13-4f76-4562-ab15-67e65b7a9f14" PROTECTEDTITLECACHE="false" TITLECACHE="Abies alba" FULLTITLECACHE="Abies alba" PARSINGPROBLEM="0" PROBLEMENDS="-1" PROBLEMSTARTS="-1" PROTECTEDFULLTITLECACHE="false" AUTHORSHIPCACHE="" BINOMHYBRID="false" HYBRIDFORMULA="false" MONOMHYBRID="false" NAMECACHE="Abies alba" PROTECTEDAUTHORSHIPCACHE="false" PROTECTEDNAMECACHE="true" TRINOMHYBRID="false" ANAMORPHIC="false" HOMOTYPICALGROUP_ID="1001" RANK_ID="777"/>
  <TAXONNAMEBASE DTYPE="BotanicalName" ID="1002" CREATED="2012-06-07 20:44:50.0" UUID="311ede14-956e-4277-9715-42f0997dad98" PROTECTEDTITLECACHE="false" TITLECACHE="Abies balsamea" FULLTITLECACHE="Abies balsamea" PARSINGPROBLEM="0" PROBLEMENDS="-1" PROBLEMSTARTS="-1" PROTECTEDFULLTITLECACHE="false" AUTHORSHIPCACHE="" BINOMHYBRID="false" HYBRIDFORMULA="false" MONOMHYBRID="false" NAMECACHE="Abies balsamea" PROTECTEDAUTHORSHIPCACHE="false" PROTECTEDNAMECACHE="true" TRINOMHYBRID="false" ANAMORPHIC="false" HOMOTYPICALGROUP_ID="1002" RANK_ID="777"/>
  <TAXONNAMEBASE DTYPE="BotanicalName" ID="1003" CREATED="2012-06-07 20:44:50.0" UUID="c50ec7aa-72c0-4074-8430-5937d0014e8c" PROTECTEDTITLECACHE="false" TITLECACHE="Abies grandis" FULLTITLECACHE="Abies grandis" PARSINGPROBLEM="0" PROBLEMENDS="-1" PROBLEMSTARTS="-1" PROTECTEDFULLTITLECACHE="false" AUTHORSHIPCACHE="" BINOMHYBRID="false" HYBRIDFORMULA="false" MONOMHYBRID="false" NAMECACHE="Abies grandis" PROTECTEDAUTHORSHIPCACHE="false" PROTECTEDNAMECACHE="true" TRINOMHYBRID="false" ANAMORPHIC="false" HOMOTYPICALGROUP_ID="1003" RANK_ID="777"/>
  <TAXONNAMEBASE DTYPE="BotanicalName" ID="1004" CREATED="2012-06-07 20:44:50.0" UUID="52baaa58-a7e7-4530-acc6-aac7275d93f1" PROTECTEDTITLECACHE="false" TITLECACHE="Abies kawakamii" FULLTITLECACHE="Abies kawakamii" PARSINGPROBLEM="0" PROBLEMENDS="-1" PROBLEMSTARTS="-1" PROTECTEDFULLTITLECACHE="false" AUTHORSHIPCACHE="" BINOMHYBRID="false" HYBRIDFORMULA="false" MONOMHYBRID="false" NAMECACHE="Abies kawakamii" PROTECTEDAUTHORSHIPCACHE="false" PROTECTEDNAMECACHE="true" TRINOMHYBRID="false" ANAMORPHIC="false" HOMOTYPICALGROUP_ID="1004" RANK_ID="777"/>
  <TAXONNAMEBASE DTYPE="BotanicalName" ID="1005" CREATED="2012-06-07 20:44:50.0" UUID="55f77a1e-0055-4e98-a38b-59670509c0c7" PROTECTEDTITLECACHE="false" TITLECACHE="Abies subalpina" FULLTITLECACHE="Abies subalpina" PARSINGPROBLEM="0" PROBLEMENDS="-1" PROBLEMSTARTS="-1" PROTECTEDFULLTITLECACHE="false" AUTHORSHIPCACHE="" BINOMHYBRID="false" HYBRIDFORMULA="false" MONOMHYBRID="false" NAMECACHE="Abies subalpina" PROTECTEDAUTHORSHIPCACHE="false" PROTECTEDNAMECACHE="true" TRINOMHYBRID="false" ANAMORPHIC="false" HOMOTYPICALGROUP_ID="1005" RANK_ID="777"/>
  <TAXONNAMEBASE DTYPE="BotanicalName" ID="1006" CREATED="2012-06-07 20:44:50.0" UUID="e2bd6791-cefa-4026-9991-2fc1cb82477a" PROTECTEDTITLECACHE="false" TITLECACHE="Abies lasiocarpa" FULLTITLECACHE="Abies lasiocarpa" PARSINGPROBLEM="0" PROBLEMENDS="-1" PROBLEMSTARTS="-1" PROTECTEDFULLTITLECACHE="false" AUTHORSHIPCACHE="" BINOMHYBRID="false" HYBRIDFORMULA="false" MONOMHYBRID="false" NAMECACHE="Abies lasiocarpa" PROTECTEDAUTHORSHIPCACHE="false" PROTECTEDNAMECACHE="true" TRINOMHYBRID="false" ANAMORPHIC="false" HOMOTYPICALGROUP_ID="1006" RANK_ID="777"/>
  <SYNONYMRELATIONSHIP ID="1000" CREATED="2012-06-07 20:44:50.0" UUID="e4b9ac42-abda-4c2a-8322-8ba99b64a571" DOUBTFUL="false" PARTIAL="false" PROPARTE="false" RELATEDFROM_ID="1005" RELATEDTO_ID="1006" TYPE_ID="872"/>
  <REFERENCE ID="1000" CREATED="2012-06-07 20:44:50.0" UUID="fcd0ec3b-ad65-4845-840a-2f060202fad1" PROTECTEDTITLECACHE="false" TITLECACHE="" NOMENCLATURALLYRELEVANT="false" PARSINGPROBLEM="0" PROBLEMENDS="-1" PROBLEMSTARTS="-1" REFTYPE="1"/>
  <DESCRIPTIONELEMENTBASE DTYPE="CommonTaxonName" ID="1000" CREATED="2012-06-07 20:44:50.0" UUID="42a591b4-ef5c-4e51-a664-7ab71a6beb2e" NAME="silver fir" FEATURE_ID="946" INDESCRIPTION_ID="1000" LANGUAGE_ID="124"/>
  <DESCRIPTIONELEMENTBASE DTYPE="CommonTaxonName" ID="1001" CREATED="2012-06-07 20:44:50.0" UUID="6df82f82-2646-43a6-a128-f0734970dfcb" NAME="Wei&#223;tanne" FEATURE_ID="946" INDESCRIPTION_ID="1000" LANGUAGE_ID="46"/>
  <DESCRIPTIONELEMENTBASE DTYPE="TextData" ID="1002" CREATED="2012-06-07 20:44:50.0" UUID="e24ec37f-f26f-48cd-aff4-4a37b362b18a" FEATURE_ID="966" INDESCRIPTION_ID="1001"/>
  <DESCRIPTIONELEMENTBASE DTYPE="TextData" ID="1003" CREATED="2012-06-07 20:44:50.0" UUID="da3af6ac-b63c-43f8-925f-7da4bd898fbc" FEATURE_ID="966" INDESCRIPTION_ID="1001"/>
  <DESCRIPTIONBASE DTYPE="TaxonDescription" ID="1000" CREATED="2012-06-07 20:44:50.0" UUID="881b9c80-626d-47a6-b308-a63ee5f4178f" PROTECTEDTITLECACHE="false" TITLECACHE="Taxon description for Abies alba" IMAGEGALLERY="false" TAXON_ID="1001"/>
  <DESCRIPTIONBASE DTYPE="TaxonDescription" ID="1001" CREATED="2012-06-07 20:44:50.0" UUID="943742c4-b111-418e-ad4d-8e1e5c26b46a" PROTECTEDTITLECACHE="false" TITLECACHE="Taxon description for Abies balsamea" IMAGEGALLERY="false" TAXON_ID="1002"/>
  <AGENTBASE/>
  <HOMOTYPICALGROUP ID="1000" CREATED="2012-06-07 20:44:50.0" UUID="aaede661-42bb-449a-946a-e9e914f51819"/>
  <HOMOTYPICALGROUP ID="1001" CREATED="2012-06-07 20:44:50.0" UUID="51557668-15ab-4fd9-a4db-480e4fde1c24"/>
  <HOMOTYPICALGROUP ID="1002" CREATED="2012-06-07 20:44:50.0" UUID="b4f4f488-73c1-4567-9ea8-69dd56ff7bec"/>
  <HOMOTYPICALGROUP ID="1003" CREATED="2012-06-07 20:44:50.0" UUID="cd0ee95f-d8e6-485b-b974-a5a5877f4bce"/>
  <HOMOTYPICALGROUP ID="1004" CREATED="2012-06-07 20:44:50.0" UUID="dd45fb9b-fc1c-410e-8132-7bf44f7b7618"/>
  <HOMOTYPICALGROUP ID="1005" CREATED="2012-06-07 20:44:50.0" UUID="1e4f6c66-cb49-44d7-b5b8-a88f14dde9e5"/>
  <HOMOTYPICALGROUP ID="1006" CREATED="2012-06-07 20:44:50.0" UUID="b47395c8-4909-457f-a76a-808fa8dd79da"/>
  <CLASSIFICATION/>
  <LANGUAGESTRING ID="1000" CREATED="2012-06-07 20:44:50.0" UUID="dac6f6c3-21c8-48a2-ac0b-ac626396f369" TEXT="Die Balsam-Tanne (Abies balsamea) ist eine Pflanzenart aus der Gattung der Tannen (Abies). Sie w&#228;chst im nord&#246;stlichen Nordamerika, wo sie sowohl Tief- als auch Bergland besiedelt. Sie gilt als relativ anspruchslos gegen&#252;ber dem Standort und ist frosthart. In vielen Teilen des nat&#252;rlichen Verbreitungsgebietes stellt sie die Klimaxbaumart dar." LANGUAGE_ID="46"/>
  <LANGUAGESTRING ID="1001" CREATED="2012-06-07 20:44:50.0" UUID="b2418740-f130-4d9f-8e1c-9ae0c0a1981b" TEXT="&#1041;&#1072;&#1083;&#1100;&#1079;&#1072;&#1084; &#1085;&#1100;&#1099;&#1074; (&#1083;&#1072;&#1090;. Abies balsamea) &#8211; &#1073;&#1099;&#1076;&#1084;&#1072;&#1089;&#1089;&#1101;&#1079;&#1083;&#1255;&#1085; &#1087;&#1086;&#1078;&#1091;&#1084; &#1082;&#1086;&#1090;&#1099;&#1088;&#1080;&#1089;&#1100; &#1085;&#1100;&#1099;&#1074; &#1091;&#1074;&#1090;&#1099;&#1088;&#1099;&#1085; &#1090;&#1086;&#1088;&#1100;&#1103; &#1074;&#1080;&#1076;. &#1053;&#1100;&#1099;&#1074;&#1087;&#1091;&#1099;&#1089; &#1073;&#1099;&#1076;&#1084;&#1255; 14&#8211;20 &#1084;&#1077;&#1090;&#1088;&#1072; &#1074;&#1099;&#1083;&#1099;&#1085;&#1072; &#1076;&#1072; &#1086;&#1074;&#1083;&#1255; 10&#8211;60 &#1089;&#1084; &#1082;&#1099;&#1079;&#1072; &#1076;&#1080;&#1072;&#1084;&#1077;&#1090;&#1088;&#1099;&#1085;. &#1053;&#1100;&#1099;&#1074;&#1087;&#1091; &#1087;&#1072;&#1085;&#1090;&#1072;&#1089;&#1100;&#1255; &#1054;&#1081;&#1074;&#1099;&#1074; &#1040;&#1084;&#1077;&#1088;&#1080;&#1082;&#1072;&#1099;&#1085;." LANGUAGE_ID="286"/>
  <DESCRIPTIONELEMENTBASE_LANGUAGESTRING DESCRIPTIONELEMENTBASE_ID="1002" MULTILANGUAGETEXT_ID="1000" MULTILANGUAGETEXT_MAPKEY_ID="46"/>
  <DESCRIPTIONELEMENTBASE_LANGUAGESTRING DESCRIPTIONELEMENTBASE_ID="1003" MULTILANGUAGETEXT_ID="1001" MULTILANGUAGETEXT_MAPKEY_ID="286"/>
</dataset>
