<?xml version="1.0" encoding="UTF-8"?>
<beans xmlns="http://www.springframework.org/schema/beans"
	xmlns:xsi="http://www.w3.org/2001/XMLSchema-instance"
	xmlns:context="http://www.springframework.org/schema/context"
	xsi:schemaLocation="http://www.springframework.org/schema/beans
    http://www.springframework.org/schema/beans/spring-beans-2.5.xsd
    http://www.springframework.org/schema/context
    http://www.springframework.org/schema/context/spring-context-2.5.xsd">

  <bean id="dataSource"  lazy-init="true" class="eu.etaxonomy.cdm.remote.service.UpdatableRoutingDataSource">
    	<property name="targetDataSources">
	      <map key-type="java.lang.String">
	         <entry key="cichorieae" value-ref="cichorieaeDataSource"/>
	         <entry key="palmae" value-ref="palmaeDataSource"/>
	         <entry key="diptera" value-ref="dipteraDataSource"/>
	      </map>
   		</property>
   		<property name="defaultTargetDataSource" ref="cichorieaeDataSource"/>
   </bean>

    <bean id="cichorieaeDataSource"  lazy-init="true" class="org.springframework.jdbc.datasource.DriverManagerDataSource">
        <property name="driverClassName" value="com.mysql.jdbc.Driver"/>
        <property name="username" value="${wp7virtual.usr}"/>
        <property name="password" value="${wp7virtual.pwd}"/>
        <property name="url" value="jdbc:mysql://${wp7virtual.host}/cdm_import_cichorieae"/>
    </bean>
    <bean id="palmaeDataSource"  lazy-init="true" class="org.springframework.jdbc.datasource.DriverManagerDataSource">
        <property name="driverClassName" value="com.mysql.jdbc.Driver"/>
        <property name="username" value="${wp7virtual.usr}"/>
        <property name="password" value="${wp7virtual.pwd}"/>
        <property name="url" value="jdbc:mysql://${wp7virtual.host}/cdm_import_palmae"/>
    </bean>

    <bean id="dipteraDataSource"  lazy-init="true" class="org.springframework.jdbc.datasource.DriverManagerDataSource">
        <property name="driverClassName" value="com.mysql.jdbc.Driver"/>
        <property name="username" value="${wp7virtual.usr}"/>
        <property name="password" value="${wp7virtual.pwd}"/>
        <property name="url" value="jdbc:mysql://${wp7virtual.host}/cdm_import_diptera"/>
    </bean>
    
    <!-- This configures default properties, which can overridden with the file specified by the location property -->
    <bean id="hibernateProperties" 
        class="org.springframework.beans.factory.config.PropertiesFactoryBean">
        <property name="properties">
            <props>
                <prop key="hibernate.hbm2ddl.auto">validate</prop>
                <prop key="hibernate.dialect">org.hibernate.dialect.MySQLDialect</prop>
                <prop key="hibernate.cache.provider_class">org.hibernate.cache.NoCacheProvider</prop>
                <prop key="hibernate.show_sql">false</prop>
                <prop key="hibernate.format_sql">false</prop>
            </props>
        </property>
    </bean>

</beans>